image_file_validator/__init__.py
image_file_validator/image_file_validator.py
image_file_validator-0.0.6.dist-info/LICENSE.txt
image_file_validator-0.0.6.dist-info/METADATA
image_file_validator-0.0.6.dist-info/WHEEL
image_file_validator-0.0.6.dist-info/top_level.txt
image_file_validator-0.0.6.dist-info/RECORD
