Metadata-Version: 2.1
Name: image-file-validator
Version: 0.0.6
Summary: A simple pluggable image file validator for all type of python applications
Home-page: https://github.com/Zeecoworld/image-file-validator
Author: Isaac Yakubu
Author-email: engrisaac1234@gmail.com
License: MIT
Keywords: image-validate,image,image file validation
Classifier: Development Status :: 5 - Production/Stable
Classifier: Intended Audience :: Education
Classifier: Operating System :: Microsoft :: Windows :: Windows 10
Classifier: License :: OSI Approved :: MIT License
Classifier: Programming Language :: Python :: 3
License-File: LICENSE.txt
Requires-Dist: filetype
